btledstrip/__init__.py
btledstrip/controllers.py
btledstrip/dev.py
btledstrip/typing.py
btledstrip/demonstrations/__init__.py
btledstrip/demonstrations/melk.py
btledstrip-0.1.1.dist-info/METADATA
btledstrip-0.1.1.dist-info/WHEEL
btledstrip-0.1.1.dist-info/licenses/LICENSE
btledstrip-0.1.1.dist-info/RECORD
